neurosift_jp/__init__.py
neurosift_jp/_frontend.py
neurosift_jp/_version.py
neurosift_jp/example.py
neurosift_jp/widgets/NeurosiftFigure.py
neurosift_jp/widgets/__init__.py
neurosift_jp-0.1.5.data/data/share/jupyter/labextensions/neurosift-jp/package.json
neurosift_jp-0.1.5.data/data/share/jupyter/labextensions/neurosift-jp/static/1234.3f018d35f69768e287ec.js
neurosift_jp-0.1.5.data/data/share/jupyter/labextensions/neurosift-jp/static/1236.cc0f20a69ef5a6aef50d.js
neurosift_jp-0.1.5.data/data/share/jupyter/labextensions/neurosift-jp/static/1236.cc0f20a69ef5a6aef50d.js.LICENSE.txt
neurosift_jp-0.1.5.data/data/share/jupyter/labextensions/neurosift-jp/static/1268.bf2a72019e78cefd47e7.js
neurosift_jp-0.1.5.data/data/share/jupyter/labextensions/neurosift-jp/static/1346.54616c435ed6ba2b0e61.js
neurosift_jp-0.1.5.data/data/share/jupyter/labextensions/neurosift-jp/static/1377.05633afdfb3f901eaee1.js
neurosift_jp-0.1.5.data/data/share/jupyter/labextensions/neurosift-jp/static/1868.34051752c234212ac87b.js
neurosift_jp-0.1.5.data/data/share/jupyter/labextensions/neurosift-jp/static/2206.167d96685b35741667d0.js
neurosift_jp-0.1.5.data/data/share/jupyter/labextensions/neurosift-jp/static/2422.bdfa6a514a1c4be2a4dd.js
neurosift_jp-0.1.5.data/data/share/jupyter/labextensions/neurosift-jp/static/2422.bdfa6a514a1c4be2a4dd.js.LICENSE.txt
neurosift_jp-0.1.5.data/data/share/jupyter/labextensions/neurosift-jp/static/311.24ab8b3cb08c638fd086.js
neurosift_jp-0.1.5.data/data/share/jupyter/labextensions/neurosift-jp/static/3364.07b9dc4d7d46256131b2.js
neurosift_jp-0.1.5.data/data/share/jupyter/labextensions/neurosift-jp/static/3558.aae3f1b85c4bb410a347.js
neurosift_jp-0.1.5.data/data/share/jupyter/labextensions/neurosift-jp/static/4033.2c353011c2191e2dd2e8.js
neurosift_jp-0.1.5.data/data/share/jupyter/labextensions/neurosift-jp/static/4125.d0dab86345f16722287a.js
neurosift_jp-0.1.5.data/data/share/jupyter/labextensions/neurosift-jp/static/4125.d0dab86345f16722287a.js.LICENSE.txt
neurosift_jp-0.1.5.dist-info/METADATA
neurosift_jp-0.1.5.dist-info/WHEEL
neurosift_jp-0.1.5.dist-info/licenses/LICENSE
neurosift_jp-0.1.5.dist-info/RECORD
