Metadata-Version: 2.3
Name: neurosift_jp
Version: 0.1.5
Summary: Neurosift Jupyter extension
Project-URL: Homepage, https://github.com/magland/neurosift-jp
Project-URL: Bug Tracker, https://github.com/magland/neurosift-jp/issues
Project-URL: Repository, https://github.com/magland/neurosift-jp.git
Author-email: Jeremy Magland <jmagland@flatironinstitute.org>
License: BSD 3-Clause License
Keywords: jupyter,jupyterlab,jupyterlab-extension
Classifier: Framework :: Jupyter
Classifier: Framework :: Jupyter :: JupyterLab
Classifier: Framework :: Jupyter :: JupyterLab :: 4
Classifier: Framework :: Jupyter :: JupyterLab :: Extensions
Classifier: Framework :: Jupyter :: JupyterLab :: Extensions :: Prebuilt
Classifier: License :: OSI Approved :: BSD License
Classifier: Programming Language :: Python
Classifier: Programming Language :: Python :: 3
Classifier: Programming Language :: Python :: 3.8
Classifier: Programming Language :: Python :: 3.9
Classifier: Programming Language :: Python :: 3.10
Classifier: Programming Language :: Python :: 3.11
Classifier: Programming Language :: Python :: 3.12
Requires-Python: >=3.8
